pysoc/__init__.py
pysoc/bnb/__init__.py
pysoc/soc/__init__.py
pysoc/tests/__init__.py
pysoc/tests/bnb/__init__.py
pysoc/tests/bnb/bnb_pytest/__init__.py
pysoc/tests/bnb/bnb_pytest/test_bnbmatlab.py
pysoc/tests/soc/__init__.py
pysoc/tests/soc/soc_pytest/__init__.py
pysoc/tests/soc/soc_pytest/columtetst.py
pysoc/tests/soc/soc_pytest/test_socmatlab.py
pysoc/utils/__init__.py
pysoc/utils/matrixdivide.py
pysoc-0.0.3.dist-info/LICENSE
pysoc-0.0.3.dist-info/METADATA
pysoc-0.0.3.dist-info/WHEEL
pysoc-0.0.3.dist-info/top_level.txt
pysoc-0.0.3.dist-info/RECORD
